<?xml version="1.0" encoding="UTF-8" ?>
<ProductPrices>
	<ProductPrice>
		<product>1231</product>
		<productcode>65456P</productcode>
		<price>
			<pricecategory>-1</pricecategory>
			<pricecategoryName>Lista ár</pricecategoryName>
			<priceCurrency>HUF</priceCurrency>
			<quantityunit>db</quantityunit>
			<value>14580</value>
			<validfrom>2010-07-12</validfrom>
		</price>
		<price>
			<pricecategory>-1</pricecategory>
			<pricecategoryName>Lista ár</pricecategoryName>
			<priceCurrency>EUR</priceCurrency>
			<quantityunit>kg</quantityunit>
			<value>12.5</value>
			<validfrom>2010-07-12</validfrom>
		</price>
		<price>
			<pricecategory>4</pricecategory>
			<pricecategoryName>Nagyker ár</pricecategoryName>
			<priceCurrency>HUF</priceCurrency>
			<quantityunit>db</quantityunit>
			<value>11580</value>
			<validfrom>2010-07-12</validfrom>
		</price>
	</ProductPrice>
	<ProductPrice>
		<product>1232</product>
		<productcode>65786P</productcode>
      <price>
        <pricecategory>-1</pricecategory>
        <pricecategoryName>Lista ár</pricecategoryName>
        <priceCurrency>HUF</priceCurrency>
        <quantityunit>db</quantityunit>
        <value>14580</value>
		<validfrom>2010-07-12</validfrom>
      </price>
      <price>
        <pricecategory>-1</pricecategory>
        <pricecategoryName>Lista ár</pricecategoryName>
        <priceCurrency>EUR</priceCurrency>
        <quantityunit>kg</quantityunit>
        <value>12.5</value>
		<validfrom>2010-07-12</validfrom>
      </price>
      <price>
       <pricecategory>4</pricecategory>
        <pricecategoryName>Nagyker ár</pricecategoryName>
        <priceCurrency>HUF</priceCurrency>
        <quantityunit>db</quantityunit>
        <value>11580</value>
		<validfrom>2010-07-12</validfrom>
      </price>
	</ProductPrice>
</ProductPrices>
